project/m2/rtl/interface.sv
// ============================================================
// interface.sv
// SPI Slave Interface Module
// ECE 410/510 — Spring 2026
// ============================================================
//
// *** NAMING NOTE ***
// 'interface' is a reserved keyword in SystemVerilog.
// The top module in this file is therefore named spi_slave.
// The testbench (tb_interface.sv) instantiates spi_slave.
// See project/m2/README.md §Deviations for full explanation.
//
// TOP MODULE: spi_slave
//
// PURPOSE:
//   SPI slave implementing Mode 0 (CPOL=0, CPHA=0).
//   Provides a 4-entry × 8-bit register file accessible
//   from an SPI master. In the full chiplet this register
//   file bridges the MCU host to the compute_core:
//     reg[0] — feature byte staging (testing placeholder)
//     reg[1] — control  (bit 0 = start compute)
//     reg[2] — result byte (argmax label from compute core)
//     reg[3] — status   (bit 0 = done)
//
// TRANSACTION FORMAT (16 bits per CS assertion):
//   Byte 0 (first 8 SCLKs) : { R/W#[7], ADDR[6:0] }
//     R/W# = 0 → write;  R/W# = 1 → read
//   Byte 1 (next  8 SCLKs) : data (write) / don't-care (read)
//   During byte 1 of a READ, MISO shifts out reg[ADDR] MSB-first.
//
// REGISTER MAP:
//   Addr 0x00  RW  feature_byte  — MFCC feature staging register
//   Addr 0x01  RW  control       — bit[0]: start inference pulse
//   Addr 0x02  RO  result        — inference argmax label
//   Addr 0x03  RO  status        — bit[0]: inference done flag
//
// PORTS:
//   clk       in  1   system clock (must be ≥ 4× SCLK for sync)
//   rst_n     in  1   synchronous active-low reset
//   sclk      in  1   SPI clock from master (CPOL=0: idle low)
//   cs_n      in  1   chip select, active low
//   mosi      in  1   master→slave data, sampled on SCLK rising
//   miso      out 1   slave→master data, updated on SCLK falling
//   bus_addr  out 2   register address of last completed transaction
//   bus_wdata out 8   write data of last completed transaction
//   bus_wr    out 1   one-cycle write strobe (system clock domain)
//   bus_rdata in  8   read data provided by connected logic
//
// CLOCK DOMAIN: single system clock (clk).
//   SCLK and CS_N are synchronised via 2-FF synchronisers.
//   Requires system clock ≥ 4× SCLK.
// RESET: synchronous, active-low (rst_n).
//
// SPI MODE: 0 (CPOL=0 — clock idles low;
//               CPHA=0 — data sampled on rising SCLK edge)
// ============================================================

`timescale 1ns/1ps

module spi_slave #(
    parameter int N_REGS = 4,   // number of 8-bit registers
    parameter int AW     = 2    // address bits = log2(N_REGS)
) (
    input  logic        clk,
    input  logic        rst_n,

    // SPI pins
    input  logic        sclk,
    input  logic        cs_n,
    input  logic        mosi,
    output logic        miso,

    // Internal register bus
    output logic [AW-1:0] bus_addr,
    output logic [7:0]    bus_wdata,
    output logic          bus_wr,
    input  logic [7:0]    bus_rdata
);

    // ----------------------------------------------------------
    // 2-FF synchronisers for sclk, cs_n, mosi
    // ----------------------------------------------------------
    logic sclk_s1, sclk_s2, sclk_s3;
    logic csn_s1,  csn_s2,  csn_s3;
    logic mosi_s1, mosi_s2;

    always_ff @(posedge clk) begin
        if (!rst_n) begin
            {sclk_s1, sclk_s2, sclk_s3} <= 3'b0;
            {csn_s1,  csn_s2,  csn_s3}  <= 3'b111;
            {mosi_s1, mosi_s2}            <= 2'b0;
        end else begin
            sclk_s1 <= sclk;  sclk_s2 <= sclk_s1;  sclk_s3 <= sclk_s2;
            csn_s1  <= cs_n;  csn_s2  <= csn_s1;   csn_s3  <= csn_s2;
            mosi_s1 <= mosi;  mosi_s2 <= mosi_s1;
        end
    end

    // Edge detects (one sys-clock pulse each)
    wire sclk_rise = ( sclk_s2 & ~sclk_s3);   // SCLK 0→1
    wire sclk_fall = (~sclk_s2 &  sclk_s3);   // SCLK 1→0
    wire csn_fall  = (~csn_s2  &  csn_s3);    // CS_N 1→0  (start)
    wire csn_rise  = ( csn_s2  & ~csn_s3);    // CS_N 0→1  (end)

    // ----------------------------------------------------------
    // Register file
    // ----------------------------------------------------------
    logic [7:0] reg_file [0:N_REGS-1];

    // ----------------------------------------------------------
    // Shift register & bit counter
    // ----------------------------------------------------------
    logic [15:0] rx_shift;   // 16-bit RX: [15:8]=addr byte, [7:0]=data byte
    logic [7:0]  tx_shift;   // 8-bit  TX shift register
    logic [4:0]  bit_cnt;    // counts 0-15 within a transaction
    logic        rw_bit;     // captured R/W# after 8 bits
    logic [AW-1:0] addr_latch; // captured address after 8 bits

    // ----------------------------------------------------------
    // Main SPI receive / transmit logic
    // ----------------------------------------------------------
    integer i;
    always_ff @(posedge clk) begin
        if (!rst_n) begin
            rx_shift   <= 16'h0;
            tx_shift   <= 8'h0;
            bit_cnt    <= 5'h0;
            rw_bit     <= 1'b0;
            addr_latch <= '0;
            miso       <= 1'b0;
            bus_wr     <= 1'b0;
            bus_addr   <= '0;
            bus_wdata  <= 8'h0;
            for (i = 0; i < N_REGS; i = i+1)
                reg_file[i] <= 8'h0;
        end else begin
            bus_wr <= 1'b0;

            // --- Transaction start ---
            if (csn_fall) begin
                bit_cnt  <= 5'h0;
                rx_shift <= 16'h0;
            end

            // --- Rising SCLK: sample MOSI ---
            if (sclk_rise && !csn_s2) begin
                rx_shift <= {rx_shift[14:0], mosi_s2};
                bit_cnt  <= bit_cnt + 1'b1;

                // After 8 bits: latch addr and R/W#, load tx_shift for reads.
                // At bit_cnt==7 the 8th bit (mosi_s2) is being clocked in but
                // the non-blocking rx_shift update hasn't settled yet.
                // rw_bit  lives at rx_shift[6] (MSB of addr byte after 7 prior shifts).
                // address lives at {rx_shift[AW-2:0], mosi_s2} — the AW LSBs
                // assembled from the already-shifted bits plus the current MOSI bit.
                if (bit_cnt == 5'd7) begin
                    rw_bit     <= rx_shift[6];
                    addr_latch <= {rx_shift[AW-2:0], mosi_s2};
                    tx_shift   <= reg_file[{rx_shift[AW-2:0], mosi_s2}];
                end
            end

            // --- Falling SCLK: update MISO (shift TX) ---
            if (sclk_fall && !csn_s2) begin
                if (bit_cnt >= 5'd8) begin
                    miso     <= tx_shift[7];
                    tx_shift <= {tx_shift[6:0], 1'b0};
                end else begin
                    miso <= 1'b0;
                end
            end

            // --- Transaction end: commit write ---
            if (csn_rise) begin
                if (!rw_bit) begin
                    // Write: register address in addr_latch, data in rx_shift[7:0]
                    reg_file[addr_latch] <= rx_shift[7:0];
                    bus_addr             <= addr_latch;
                    bus_wdata            <= rx_shift[7:0];
                    bus_wr               <= 1'b1;
                end
            end
        end
    end

    // bus_rdata reflects current register value (combinational)
    assign bus_rdata = reg_file[bus_addr];

endmodule

project/m2/tb/tb_interface.sv
// ============================================================
// tb_interface.sv — Testbench for spi_slave (interface.sv)
// ECE 410/510 — Spring 2026
// Simulator: Icarus Verilog 13.0
//   iverilog -g2012 -o sim_if tb/tb_interface.sv rtl/interface.sv
//   vvp sim_if
// ============================================================
//
// TESTS:
//   Test 1 — SPI Write:
//     Write 0xA5 to register address 0x01 (control register).
//     Byte 0: 0x01  (R/W#=0, addr=0x01)
//     Byte 1: 0xA5  (data)
//     Assert reg[0x01] == 0xA5 and bus_wr strobe fires.
//
//   Test 2 — SPI Read:
//     Read back register address 0x01.
//     Byte 0: 0x81  (R/W#=1, addr=0x01)
//     Byte 1: don't-care on MOSI; capture MISO[7:0].
//     Assert captured MISO byte == 0xA5.
//
// SPI MODE 0: CPOL=0 (clock idles low), CPHA=0 (sample rising)
// SCLK frequency = sys_clk / 8  (well within 4× sync requirement)
// ============================================================

`timescale 1ns/1ps

module tb_interface;

    // ----------------------------------------------------------
    // DUT signals
    // ----------------------------------------------------------
    logic       clk, rst_n;
    logic       sclk, cs_n, mosi;
    logic       miso;
    logic [1:0] bus_addr;
    logic [7:0] bus_wdata;
    logic       bus_wr;
    logic [7:0] bus_rdata;

    // ----------------------------------------------------------
    // DUT instantiation  (module is spi_slave, file is interface.sv)
    // ----------------------------------------------------------
    spi_slave #(
        .N_REGS(4),
        .AW    (2)
    ) dut (
        .clk      (clk      ),
        .rst_n    (rst_n    ),
        .sclk     (sclk     ),
        .cs_n     (cs_n     ),
        .mosi     (mosi     ),
        .miso     (miso     ),
        .bus_addr (bus_addr ),
        .bus_wdata(bus_wdata),
        .bus_wr   (bus_wr   ),
        .bus_rdata(bus_rdata)
    );

    // ----------------------------------------------------------
    // System clock: 10 ns period (100 MHz)
    // ----------------------------------------------------------
    initial clk = 0;
    always #5 clk = ~clk;

    // ----------------------------------------------------------
    // VCD waveform dump (appended to waveform.vcd if run second;
    // tb_compute_core creates the file — this TB adds interface signals)
    // ----------------------------------------------------------
    initial begin
        $dumpfile("sim/waveform_if.vcd");
        $dumpvars(0, tb_interface);
    end

    // ----------------------------------------------------------
    // SPI master task: send 16-bit word (addr_byte + data_byte)
    // SCLK period = 8 sys-clock cycles → 80 ns
    // ----------------------------------------------------------
    task spi_transaction(
        input  logic [7:0] addr_byte,
        input  logic [7:0] data_byte,
        output logic [7:0] rx_byte
    );
        integer b;
        logic [15:0] tx_word;
        tx_word = {addr_byte, data_byte};
        rx_byte = 8'h00;

        // Assert CS_N
        @(negedge clk);
        cs_n = 1'b0;
        repeat(2) @(negedge clk);

        for (b = 15; b >= 0; b = b-1) begin
            // Setup MOSI before rising edge
            @(negedge clk);
            mosi = tx_word[b];
            sclk = 1'b0;
            repeat(3) @(negedge clk);

            // Rising edge — DUT samples MOSI
            sclk = 1'b1;
            @(negedge clk);

            // Capture MISO during data byte (bits 7..0)
            if (b < 8)
                rx_byte[b] = miso;

            repeat(3) @(negedge clk);
        end

        // Final falling edge + deassert
        sclk = 1'b0;
        repeat(2) @(negedge clk);
        cs_n = 1'b1;
        repeat(4) @(negedge clk);
    endtask

    // ----------------------------------------------------------
    // Main stimulus
    // ----------------------------------------------------------
    logic [7:0] captured;
    integer      fail_cnt;

    initial begin
        // Initialise
        rst_n = 1'b0;
        cs_n  = 1'b1;
        sclk  = 1'b0;
        mosi  = 1'b0;

        repeat(4) @(negedge clk);
        rst_n = 1'b1;
        repeat(2) @(negedge clk);

        fail_cnt = 0;

        // ========================================================
        // Test 1: Write 0xA5 to register 0x01
        // ========================================================
        $display("[TB] Test 1 — SPI Write: addr=0x01 data=0xA5");
        spi_transaction(8'h01, 8'hA5, captured);

        repeat(4) @(negedge clk);

        if (bus_wdata !== 8'hA5 || bus_addr !== 2'h1) begin
            $display("  FAIL — expected addr=0x01 wdata=0xA5, got addr=0x%0h wdata=0x%0h",
                     bus_addr, bus_wdata);
            fail_cnt = fail_cnt + 1;
        end else begin
            $display("  PASS — register write captured correctly (addr=0x%0h, data=0x%0h)",
                     bus_addr, bus_wdata);
        end

        // ========================================================
        // Test 2: Read back register 0x01 → expect 0xA5 on MISO
        // ========================================================
        $display("[TB] Test 2 — SPI Read:  addr=0x81 (R/W#=1, addr=0x01)");
        spi_transaction(8'h81, 8'h00, captured);

        if (captured !== 8'hA5) begin
            $display("  FAIL — expected MISO=0xA5, got 0x%0h", captured);
            fail_cnt = fail_cnt + 1;
        end else begin
            $display("  PASS — MISO returned 0x%0h as expected", captured);
        end

        // ========================================================
        // Summary
        // ========================================================
        $display("--------------------------------------------");
        if (fail_cnt == 0)
            $display("PASS — all SPI interface tests passed");
        else
            $display("FAIL — %0d test(s) failed", fail_cnt);
        $display("--------------------------------------------");

        #50;
        $finish;
    end

endmodule

project/m2/sim/waveform_if.vcd
$date
	Sat May  2 15:37:58 2026
$end
$version
	Icarus Verilog
$end
$timescale
	1ps
$end
$scope module tb_interface $end
$var wire 1 ! miso $end
$var wire 1 " bus_wr $end
$var wire 8 # bus_wdata [7:0] $end
$var wire 2 $ bus_addr [1:0] $end
$var reg 8 % bus_rdata [7:0] $end
$var reg 8 & captured [7:0] $end
$var reg 1 ' clk $end
$var reg 1 ( cs_n $end
$var reg 1 ) mosi $end
$var reg 1 * rst_n $end
$var reg 1 + sclk $end
$var integer 32 , fail_cnt [31:0] $end
$scope module dut $end
$var wire 8 - bus_rdata [7:0] $end
$var wire 1 ' clk $end
$var wire 1 ( cs_n $end
$var wire 1 . csn_fall $end
$var wire 1 / csn_rise $end
$var wire 1 ) mosi $end
$var wire 1 * rst_n $end
$var wire 1 + sclk $end
$var wire 1 0 sclk_fall $end
$var wire 1 1 sclk_rise $end
$var parameter 32 2 AW $end
$var parameter 32 3 N_REGS $end
$var reg 2 4 addr_latch [1:0] $end
$var reg 5 5 bit_cnt [4:0] $end
$var reg 2 6 bus_addr [1:0] $end
$var reg 8 7 bus_wdata [7:0] $end
$var reg 1 " bus_wr $end
$var reg 1 8 csn_s1 $end
$var reg 1 9 csn_s2 $end
$var reg 1 : csn_s3 $end
$var reg 1 ! miso $end
$var reg 1 ; mosi_s1 $end
$var reg 1 < mosi_s2 $end
$var reg 1 = rw_bit $end
$var reg 16 > rx_shift [15:0] $end
$var reg 1 ? sclk_s1 $end
$var reg 1 @ sclk_s2 $end
$var reg 1 A sclk_s3 $end
$var reg 8 B tx_shift [7:0] $end
$var integer 32 C i [31:0] $end
$upscope $end
$scope task spi_transaction $end
$var reg 8 D addr_byte [7:0] $end
$var reg 8 E data_byte [7:0] $end
$var reg 8 F rx_byte [7:0] $end
$var reg 16 G tx_word [15:0] $end
$var integer 32 H b [31:0] $end
$upscope $end
$upscope $end
$enddefinitions $end
$comment Show the parameter values. $end
$dumpall
b100 3
b10 2
$end
#0
$dumpvars
bx H
bx G
bx F
bx E
bx D
bx C
bx B
xA
x@
x?
bx >
x=
x<
x;
x:
x9
x8
bx 7
bx 6
bx 5
bx 4
x1
x0
x/
x.
bx -
bx ,
0+
0*
0)
1(
0'
bx &
bx %
bx $
bx #
x"
x!
$end
#5000
0.
0/
01
00
0;
0<
18
19
1:
0?
0@
0A
b0 #
b0 7
b0 $
b0 6
0"
0!
b0 4
0=
b0 5
b0 B
b0 >
b100 C
1'
#10000
0'
#15000
b100 C
1'
#20000
0'
#25000
b100 C
1'
#30000
0'
#35000
b100 C
1'
#40000
1*
0'
#45000
1'
#50000
0'
#55000
1'
#60000
b0 F
b110100101 G
b10100101 E
b1 D
b0 ,
0'
#65000
1'
#70000
0(
0'
#75000
08
1'
#80000
0'
#85000
1.
09
1'
#90000
b1111 H
0'
#95000
0.
0:
1'
#100000
0'
#105000
1'
#110000
0'
#115000
1'
#120000
0'
#125000
1'
#130000
1+
0'
#135000
1?
1'
#140000
0'
#145000
11
1@
1'
#150000
0'
#155000
01
b1 5
1A
1'
#160000
0'
#165000
1'
#170000
b1110 H
0'
#175000
1'
#180000
0+
0'
#185000
0?
1'
#190000
0'
#195000
10
0@
1'
#200000
0'
#205000
00
0A
1'
#210000
1+
0'
#215000
1?
1'
#220000
0'
#225000
11
1@
1'
#230000
0'
#235000
01
b10 5
1A
1'
#240000
0'
#245000
1'
#250000
b1101 H
0'
#255000
1'
#260000
0+
0'
#265000
0?
1'
#270000
0'
#275000
10
0@
1'
#280000
0'
#285000
00
0A
1'
#290000
1+
0'
#295000
1?
1'
#300000
0'
#305000
11
1@
1'
#310000
0'
#315000
01
b11 5
1A
1'
#320000
0'
#325000
1'
#330000
b1100 H
0'
#335000
1'
#340000
0+
0'
#345000
0?
1'
#350000
0'
#355000
10
0@
1'
#360000
0'
#365000
00
0A
1'
#370000
1+
0'
#375000
1?
1'
#380000
0'
#385000
11
1@
1'
#390000
0'
#395000
01
b100 5
1A
1'
#400000
0'
#405000
1'
#410000
b1011 H
0'
#415000
1'
#420000
0+
0'
#425000
0?
1'
#430000
0'
#435000
10
0@
1'
#440000
0'
#445000
00
0A
1'
#450000
1+
0'
#455000
1?
1'
#460000
0'
#465000
11
1@
1'
#470000
0'
#475000
01
b101 5
1A
1'
#480000
0'
#485000
1'
#490000
b1010 H
0'
#495000
1'
#500000
0+
0'
#505000
0?
1'
#510000
0'
#515000
10
0@
1'
#520000
0'
#525000
00
0A
1'
#530000
1+
0'
#535000
1?
1'
#540000
0'
#545000
11
1@
1'
#550000
0'
#555000
01
b110 5
1A
1'
#560000
0'
#565000
1'
#570000
b1001 H
0'
#575000
1'
#580000
0+
0'
#585000
0?
1'
#590000
0'
#595000
10
0@
1'
#600000
0'
#605000
00
0A
1'
#610000
1+
0'
#615000
1?
1'
#620000
0'
#625000
11
1@
1'
#630000
0'
#635000
01
b111 5
1A
1'
#640000
0'
#645000
1'
#650000
b1000 H
0'
#655000
1'
#660000
0+
1)
0'
#665000
1;
0?
1'
#670000
0'
#675000
10
1<
0@
1'
#680000
0'
#685000
00
0A
1'
#690000
1+
0'
#695000
1?
1'
#700000
0'
#705000
11
1@
1'
#710000
0'
#715000
01
b1 4
b1000 5
b1 >
1A
1'
#720000
0'
#725000
1'
#730000
b111 H
0'
#735000
1'
#740000
0+
0'
#745000
0?
1'
#750000
0'
#755000
10
0@
1'
#760000
0'
#765000
00
0A
1'
#770000
1+
0'
#775000
1?
1'
#780000
0'
#785000
11
1@
1'
#790000
0'
#795000
01
b1001 5
b11 >
1A
1'
#800000
0'
#805000
1'
#810000
b110 H
0'
#815000
1'
#820000
0+
0)
0'
#825000
0;
0?
1'
#830000
0'
#835000
10
0<
0@
1'
#840000
0'
#845000
00
0A
1'
#850000
1+
0'
#855000
1?
1'
#860000
0'
#865000
11
1@
1'
#870000
0'
#875000
01
b1010 5
b110 >
1A
1'
#880000
0'
#885000
1'
#890000
b101 H
0'
#895000
1'
#900000
0+
1)
0'
#905000
1;
0?
1'
#910000
0'
#915000
10
1<
0@
1'
#920000
0'
#925000
00
0A
1'
#930000
1+
0'
#935000
1?
1'
#940000
0'
#945000
11
1@
1'
#950000
0'
#955000
01
b1011 5
b1101 >
1A
1'
#960000
0'
#965000
1'
#970000
b100 H
0'
#975000
1'
#980000
0+
0)
0'
#985000
0;
0?
1'
#990000
0'
#995000
10
0<
0@
1'
#1000000
0'
#1005000
00
0A
1'
#1010000
1+
0'
#1015000
1?
1'
#1020000
0'
#1025000
11
1@
1'
#1030000
0'
#1035000
01
b1100 5
b11010 >
1A
1'
#1040000
0'
#1045000
1'
#1050000
b11 H
0'
#1055000
1'
#1060000
0+
0'
#1065000
0?
1'
#1070000
0'
#1075000
10
0@
1'
#1080000
0'
#1085000
00
0A
1'
#1090000
1+
0'
#1095000
1?
1'
#1100000
0'
#1105000
11
1@
1'
#1110000
0'
#1115000
01
b1101 5
b110100 >
1A
1'
#1120000
0'
#1125000
1'
#1130000
b10 H
0'
#1135000
1'
#1140000
0+
1)
0'
#1145000
1;
0?
1'
#1150000
0'
#1155000
10
1<
0@
1'
#1160000
0'
#1165000
00
0A
1'
#1170000
1+
0'
#1175000
1?
1'
#1180000
0'
#1185000
11
1@
1'
#1190000
0'
#1195000
01
b1110 5
b1101001 >
1A
1'
#1200000
0'
#1205000
1'
#1210000
b1 H
0'
#1215000
1'
#1220000
0+
0)
0'
#1225000
0;
0?
1'
#1230000
0'
#1235000
10
0<
0@
1'
#1240000
0'
#1245000
00
0A
1'
#1250000
1+
0'
#1255000
1?
1'
#1260000
0'
#1265000
11
1@
1'
#1270000
0'
#1275000
01
b1111 5
b11010010 >
1A
1'
#1280000
0'
#1285000
1'
#1290000
b0 H
0'
#1295000
1'
#1300000
0+
1)
0'
#1305000
1;
0?
1'
#1310000
0'
#1315000
10
1<
0@
1'
#1320000
0'
#1325000
00
0A
1'
#1330000
1+
0'
#1335000
1?
1'
#1340000
0'
#1345000
11
1@
1'
#1350000
0'
#1355000
01
b10000 5
b110100101 >
1A
1'
#1360000
0'
#1365000
1'
#1370000
0+
b11111111111111111111111111111111 H
0'
#1375000
0?
1'
#1380000
0'
#1385000
10
0@
1'
#1390000
1(
0'
#1395000
00
18
0A
1'
#1400000
0'
#1405000
1/
19
1'
#1410000
0'
#1415000
0/
1"
b10100101 #
b10100101 7
b1 $
b1 6
1:
1'
#1420000
0'
#1425000
0"
1'
#1430000
b0 &
0'
#1435000
1'
#1440000
0'
#1445000
1'
#1450000
0'
#1455000
1'
#1460000
0'
#1465000
1'
#1470000
b1000000100000000 G
b0 E
b10000001 D
0'
#1475000
1'
#1480000
0(
0'
#1485000
08
1'
#1490000
0'
#1495000
1.
09
1'
#1500000
b1111 H
0'
#1505000
0.
0:
b0 >
b0 5
1'
#1510000
0'
#1515000
1'
#1520000
0'
#1525000
1'
#1530000
0'
#1535000
1'
#1540000
1+
0'
#1545000
1?
1'
#1550000
0'
#1555000
11
1@
1'
#1560000
0'
#1565000
01
1A
b1 5
b1 >
1'
#1570000
0'
#1575000
1'
#1580000
b1110 H
0'
#1585000
1'
#1590000
0+
0)
0'
#1595000
0;
0?
1'
#1600000
0'
#1605000
10
0<
0@
1'
#1610000
0'
#1615000
00
0A
1'
#1620000
1+
0'
#1625000
1?
1'
#1630000
0'
#1635000
11
1@
1'
#1640000
0'
#1645000
01
1A
b10 5
b10 >
1'
#1650000
0'
#1655000
1'
#1660000
b1101 H
0'
#1665000
1'
#1670000
0+
0'
#1675000
0?
1'
#1680000
0'
#1685000
10
0@
1'
#1690000
0'
#1695000
00
0A
1'
#1700000
1+
0'
#1705000
1?
1'
#1710000
0'
#1715000
11
1@
1'
#1720000
0'
#1725000
01
1A
b11 5
b100 >
1'
#1730000
0'
#1735000
1'
#1740000
b1100 H
0'
#1745000
1'
#1750000
0+
0'
#1755000
0?
1'
#1760000
0'
#1765000
10
0@
1'
#1770000
0'
#1775000
00
0A
1'
#1780000
1+
0'
#1785000
1?
1'
#1790000
0'
#1795000
11
1@
1'
#1800000
0'
#1805000
01
1A
b100 5
b1000 >
1'
#1810000
0'
#1815000
1'
#1820000
b1011 H
0'
#1825000
1'
#1830000
0+
0'
#1835000
0?
1'
#1840000
0'
#1845000
10
0@
1'
#1850000
0'
#1855000
00
0A
1'
#1860000
1+
0'
#1865000
1?
1'
#1870000
0'
#1875000
11
1@
1'
#1880000
0'
#1885000
01
1A
b101 5
b10000 >
1'
#1890000
0'
#1895000
1'
#1900000
b1010 H
0'
#1905000
1'
#1910000
0+
0'
#1915000
0?
1'
#1920000
0'
#1925000
10
0@
1'
#1930000
0'
#1935000
00
0A
1'
#1940000
1+
0'
#1945000
1?
1'
#1950000
0'
#1955000
11
1@
1'
#1960000
0'
#1965000
01
1A
b110 5
b100000 >
1'
#1970000
0'
#1975000
1'
#1980000
b1001 H
0'
#1985000
1'
#1990000
0+
0'
#1995000
0?
1'
#2000000
0'
#2005000
10
0@
1'
#2010000
0'
#2015000
00
0A
1'
#2020000
1+
0'
#2025000
1?
1'
#2030000
0'
#2035000
11
1@
1'
#2040000
0'
#2045000
01
1A
b111 5
b1000000 >
1'
#2050000
0'
#2055000
1'
#2060000
b1000 H
0'
#2065000
1'
#2070000
0+
1)
0'
#2075000
1;
0?
1'
#2080000
0'
#2085000
10
1<
0@
1'
#2090000
0'
#2095000
00
0A
1'
#2100000
1+
0'
#2105000
1?
1'
#2110000
0'
#2115000
11
1@
1'
#2120000
0'
#2125000
01
1A
b10100101 B
1=
b1000 5
b10000001 >
1'
#2130000
0'
#2135000
1'
#2140000
b111 H
0'
#2145000
1'
#2150000
0+
0)
0'
#2155000
0;
0?
1'
#2160000
0'
#2165000
10
0<
0@
1'
#2170000
0'
#2175000
00
b1001010 B
1!
0A
1'
#2180000
1+
0'
#2185000
1?
1'
#2190000
b10000000 F
0'
#2195000
11
1@
1'
#2200000
0'
#2205000
01
1A
b1001 5
b100000010 >
1'
#2210000
0'
#2215000
1'
#2220000
b110 H
0'
#2225000
1'
#2230000
0+
0'
#2235000
0?
1'
#2240000
0'
#2245000
10
0@
1'
#2250000
0'
#2255000
00
b10010100 B
0!
0A
1'
#2260000
1+
0'
#2265000
1?
1'
#2270000
0'
#2275000
11
1@
1'
#2280000
0'
#2285000
01
1A
b1010 5
b1000000100 >
1'
#2290000
0'
#2295000
1'
#2300000
b101 H
0'
#2305000
1'
#2310000
0+
0'
#2315000
0?
1'
#2320000
0'
#2325000
10
0@
1'
#2330000
0'
#2335000
00
b101000 B
1!
0A
1'
#2340000
1+
0'
#2345000
1?
1'
#2350000
b10100000 F
0'
#2355000
11
1@
1'
#2360000
0'
#2365000
01
1A
b1011 5
b10000001000 >
1'
#2370000
0'
#2375000
1'
#2380000
b100 H
0'
#2385000
1'
#2390000
0+
0'
#2395000
0?
1'
#2400000
0'
#2405000
10
0@
1'
#2410000
0'
#2415000
00
b1010000 B
0!
0A
1'
#2420000
1+
0'
#2425000
1?
1'
#2430000
0'
#2435000
11
1@
1'
#2440000
0'
#2445000
01
1A
b1100 5
b100000010000 >
1'
#2450000
0'
#2455000
1'
#2460000
b11 H
0'
#2465000
1'
#2470000
0+
0'
#2475000
0?
1'
#2480000
0'
#2485000
10
0@
1'
#2490000
0'
#2495000
00
b10100000 B
0A
1'
#2500000
1+
0'
#2505000
1?
1'
#2510000
0'
#2515000
11
1@
1'
#2520000
0'
#2525000
01
1A
b1101 5
b1000000100000 >
1'
#2530000
0'
#2535000
1'
#2540000
b10 H
0'
#2545000
1'
#2550000
0+
0'
#2555000
0?
1'
#2560000
0'
#2565000
10
0@
1'
#2570000
0'
#2575000
00
b1000000 B
1!
0A
1'
#2580000
1+
0'
#2585000
1?
1'
#2590000
b10100100 F
0'
#2595000
11
1@
1'
#2600000
0'
#2605000
01
1A
b1110 5
b10000001000000 >
1'
#2610000
0'
#2615000
1'
#2620000
b1 H
0'
#2625000
1'
#2630000
0+
0'
#2635000
0?
1'
#2640000
0'
#2645000
10
0@
1'
#2650000
0'
#2655000
00
b10000000 B
0!
0A
1'
#2660000
1+
0'
#2665000
1?
1'
#2670000
0'
#2675000
11
1@
1'
#2680000
0'
#2685000
01
1A
b1111 5
b100000010000000 >
1'
#2690000
0'
#2695000
1'
#2700000
b0 H
0'
#2705000
1'
#2710000
0+
0'
#2715000
0?
1'
#2720000
0'
#2725000
10
0@
1'
#2730000
0'
#2735000
00
b0 B
1!
0A
1'
#2740000
1+
0'
#2745000
1?
1'
#2750000
b10100101 F
0'
#2755000
11
1@
1'
#2760000
0'
#2765000
01
1A
b10000 5
b1000000100000000 >
1'
#2770000
0'
#2775000
1'
#2780000
0+
b11111111111111111111111111111111 H
0'
#2785000
0?
1'
#2790000
0'
#2795000
10
0@
1'
#2800000
1(
0'
#2805000
00
18
0A
0!
1'
#2810000
0'
#2815000
1/
19
1'
#2820000
0'
#2825000
0/
1:
1'
#2830000
0'
#2835000
1'
#2840000
b10100101 &
0'
