codefest/cf04/hdl/mac_correct.v
// mac_correct.v — Corrected, synthesizable SystemVerilog MAC unit
// ECE 410/510 Spring 2026 — Codefest 4 CLLM
//
// Fixes applied vs LLM outputs:
//   1. Inputs declared 'logic signed [7:0]' — no manual sign extension needed.
//   2. All ports use SystemVerilog 'logic' (not Verilog 'wire'/'reg').
//   3. Uses always_ff as required; plain 'always' rejected.
//   4. Product explicitly cast to 32-bit signed before accumulation.

module mac (
    input  logic              clk,
    input  logic              rst,
    input  logic signed [7:0] a,
    input  logic signed [7:0] b,
    output logic signed [31:0] out
);
    always_ff @(posedge clk) begin
        if (rst)
            out <= '0;
        else
            out <= out + 32'(signed'(a * b));
            // a*b: signed [7:0]*signed [7:0] = signed [15:0]
            // signed'() preserves sign; 32'() zero/sign-extends to 32 bits correctly
    end
endmodule

codefest/cf04/hdl/mac_tb.v
// mac_tb.v — Testbench for mac_correct.v
// ECE 410/510 Spring 2026 — Codefest 4 CLLM
//
// Sequence:
//   Cycles 1-3:  a=3,  b=4   → out = 12, 24, 36
//   Cycle  4:    rst=1       → out = 0
//   Cycles 5-6:  a=-5, b=2   → out = -10, -20
//
// Run: iverilog -g2012 -o mac_sim mac_tb.v mac_correct.v && ./mac_sim

`timescale 1ns/1ps

module mac_tb;
    logic        clk, rst;
    logic signed [7:0]  a, b;
    logic signed [31:0] out;

    // DUT
    mac dut (.clk(clk), .rst(rst), .a(a), .b(b), .out(out));

    // 10 ns clock
    initial clk = 0;
    always #5 clk = ~clk;

    // Task: check output on rising edge
    task check(input signed [31:0] expected, input string label);
        @(posedge clk); #1;
        if (out !== expected)
            $display("FAIL %s: got %0d, expected %0d", label, out, expected);
        else
            $display("PASS %s: out = %0d", label, out);
    endtask

    integer errors = 0;

    initial begin
        $dumpfile("mac_sim.vcd");
        $dumpvars(0, mac_tb);

        // Reset
        rst = 1; a = 0; b = 0;
        @(posedge clk); #1;
        rst = 0;

        // Phase 1: a=3, b=4 for 3 cycles → accumulates 12, 24, 36
        a = 3; b = 4;
        @(posedge clk); #1; $display("Cycle 1: out = %0d (expect 12)",  out);
        if (out !== 32'sd12)  errors++;
        @(posedge clk); #1; $display("Cycle 2: out = %0d (expect 24)",  out);
        if (out !== 32'sd24)  errors++;
        @(posedge clk); #1; $display("Cycle 3: out = %0d (expect 36)",  out);
        if (out !== 32'sd36)  errors++;

        // Phase 2: assert reset
        rst = 1; a = 0; b = 0;
        @(posedge clk); #1; $display("Cycle 4: out = %0d (expect 0 after rst)", out);
        if (out !== 32'sd0)   errors++;
        rst = 0;

        // Phase 3: a=-5, b=2 for 2 cycles → -10, -20
        a = -5; b = 2;
        @(posedge clk); #1; $display("Cycle 5: out = %0d (expect -10)", out);
        if (out !== -32'sd10) errors++;
        @(posedge clk); #1; $display("Cycle 6: out = %0d (expect -20)", out);
        if (out !== -32'sd20) errors++;

        if (errors == 0)
            $display("\n=== ALL TESTS PASSED ===");
        else
            $display("\n=== %0d TEST(S) FAILED ===", errors);

        $finish;
    end
endmodule

codefest/cf04/hdl/mac_sim.vcd
$date
	Thu Apr 23 22:18:33 2026
$end
$version
	Icarus Verilog
$end
$timescale
	1ps
$end
$scope module mac_tb $end
$var wire 32 ! out [31:0] $end
$var reg 8 " a [7:0] $end
$var reg 8 # b [7:0] $end
$var reg 1 $ clk $end
$var reg 1 % rst $end
$var integer 32 & errors [31:0] $end
$scope module dut $end
$var wire 8 ' a [7:0] $end
$var wire 8 ( b [7:0] $end
$var wire 1 $ clk $end
$var wire 1 % rst $end
$var reg 32 ) out [31:0] $end
$upscope $end
$scope task check $end
$var reg 32 * expected [31:0] $end
$upscope $end
$upscope $end
$enddefinitions $end
$comment Show the parameter values. $end
$dumpall
$end
#0
$dumpvars
bx *
bx )
b0 (
b0 '
b0 &
1%
0$
b0 #
b0 "
bx !
$end
#5000
b0 !
b0 )
1$
#6000
b100 #
b100 (
b11 "
b11 '
0%
#10000
0$
#15000
b1100 !
b1100 )
1$
#20000
0$
#25000
b11000 !
b11000 )
1$
#30000
0$
#35000
b100100 !
b100100 )
1$
#36000
b0 #
b0 (
b0 "
b0 '
1%
#40000
0$
#45000
b0 !
b0 )
1$
#46000
b10 #
b10 (
b11111011 "
b11111011 '
0%
#50000
0$
#55000
b11111111111111111111111111110110 !
b11111111111111111111111111110110 )
1$
#60000
0$
#65000
b11111111111111111111111111101100 !
b11111111111111111111111111101100 )
1$
